<?xml version="1.0" encoding="UTF-8"?>
<objects serializationModel="Studio.01.10.00">
    <object class="EncodingSetting" id="{5dfc85db-ea7b-4361-9a4a-96898e9140c3}">
        <property name="encodingFormat">
            <value>3</value>
        </property>
        <property name="quality">
            <value>37</value>
        </property>
        <relationship name="platform">
            <destination>{684bb13d-1af8-41d9-8c7e-90a0a872f50a}</destination>
        </relationship>
        <relationship name="encodable">
            <destination>{684bb13d-1af8-41d9-8c7e-90a0a872f50a}</destination>
        </relationship>
    </object>
</objects>
